README.rst
setup.cfg
setup.py
bin/solr-zkutil
bin/solr-zkutil.bat
bin/solr-zkutil.py
solr_zkutil.egg-info/PKG-INFO
solr_zkutil.egg-info/SOURCES.txt
solr_zkutil.egg-info/dependency_links.txt
solr_zkutil.egg-info/requires.txt
solr_zkutil.egg-info/top_level.txt
solr_zkutil.egg-info/zip-safe
solrzkutil/__init__.py
solrzkutil/__main__.py
solrzkutil/exceptions.py
solrzkutil/formatter.py
solrzkutil/healthy.py
solrzkutil/parser.py
solrzkutil/util.py